proportion-localised/__init__.py
proportion-localised/__main__.py
proportion-localised/__pycache__/__main__.cpython-39.pyc
proportion_localised/__init__.py
proportion_localised/__main__.py
proportion_localised-0.1.3.dist-info/LICENCE
proportion_localised-0.1.3.dist-info/METADATA
proportion_localised-0.1.3.dist-info/WHEEL
proportion_localised-0.1.3.dist-info/top_level.txt
proportion_localised-0.1.3.dist-info/RECORD
