Metadata-Version: 2.1
Name: proportion-localised
Version: 0.1.3
Summary: Proportion Localised is a novel metric for visual anomaly detection, intended to be more interpretable than existing metrics. Published in Transactions of Machine Learning Research (TMLR) 2024: VisionAD, a software package of performant anomaly detection algorithms, and Proportion Localised, an interpretable metric.
Home-page: https://github.com/alext1995/proportion-localised
Author: Alex Taylor
Author-email: alex.taylor07@hotmail.co.uk
License: UNKNOWN
Platform: UNKNOWN
Classifier: Programming Language :: Python :: 3
Classifier: License :: OSI Approved :: MIT License
Classifier: Operating System :: OS Independent
Requires-Python: >=3.6
License-File: LICENCE
